{
  "updatedAt": "2026-04-27T11:16:48.378Z",
  "source": {
    "url": "https://www.powerballgame.co.kr/"
  },
  "allTime": {
    "totalDraws": 18962,
    "lastRound": 1582810,
    "normal": {
      "1": 3347,
      "2": 3446,
      "3": 3357,
      "4": 3343,
      "5": 3388,
      "6": 3454,
      "7": 3347,
      "8": 3413,
      "9": 3308,
      "10": 3321,
      "11": 3409,
      "12": 3356,
      "13": 3392,
      "14": 3403,
      "15": 3398,
      "16": 3378,
      "17": 3350,
      "18": 3315,
      "19": 3420,
      "20": 3372,
      "21": 3449,
      "22": 3462,
      "23": 3456,
      "24": 3408,
      "25": 3416,
      "26": 3368,
      "27": 3377,
      "28": 3357
    },
    "power": {
      "0": 1863,
      "1": 1908,
      "2": 1927,
      "3": 1957,
      "4": 1923,
      "5": 1820,
      "6": 1837,
      "7": 1893,
      "8": 1939,
      "9": 1895
    },
    "select": {
      "normal": {
        "1": 3347,
        "2": 3446,
        "3": 3357,
        "4": 3343,
        "5": 3388,
        "6": 3454,
        "7": 3347,
        "8": 3413,
        "9": 3308,
        "10": 3321,
        "11": 3409,
        "12": 3356,
        "13": 3392,
        "14": 3403,
        "15": 3398,
        "16": 3378,
        "17": 3350,
        "18": 3315,
        "19": 3420,
        "20": 3372,
        "21": 3449,
        "22": 3462,
        "23": 3456,
        "24": 3408,
        "25": 3416,
        "26": 3368,
        "27": 3377,
        "28": 3357
      },
      "power": {
        "0": 1863,
        "1": 1908,
        "2": 1927,
        "3": 1957,
        "4": 1923,
        "5": 1820,
        "6": 1837,
        "7": 1893,
        "8": 1939,
        "9": 1895
      }
    },
    "sum": {
      "size": {
        "S": 5508,
        "M": 5997,
        "L": 5465
      },
      "band": {
        "A": 186,
        "B": 1262,
        "C": 1750,
        "D": 2655,
        "E": 4918,
        "F": 6199
      },
      "oddEven": {
        "ODD": 8413,
        "EVEN": 8557
      },
      "powerBand": {
        "A": 5102,
        "B": 3436,
        "C": 3284,
        "D": 5148
      }
    }
  },
  "recent": {
    "d1": {
      "windowDays": 1,
      "fromYmd": "2026-04-27",
      "toYmd": "2026-04-27",
      "totalDraws": 243,
      "select": {
        "normal": {
          "1": 43,
          "2": 32,
          "3": 47,
          "4": 34,
          "5": 46,
          "6": 47,
          "7": 44,
          "8": 48,
          "9": 50,
          "10": 44,
          "11": 48,
          "12": 37,
          "13": 36,
          "14": 47,
          "15": 39,
          "16": 37,
          "17": 38,
          "18": 39,
          "19": 45,
          "20": 53,
          "21": 41,
          "22": 42,
          "23": 39,
          "24": 43,
          "25": 41,
          "26": 51,
          "27": 57,
          "28": 47
        },
        "power": {
          "0": 26,
          "1": 24,
          "2": 31,
          "3": 24,
          "4": 24,
          "5": 17,
          "6": 26,
          "7": 32,
          "8": 21,
          "9": 18
        }
      },
      "sum": {
        "size": {
          "S": 71,
          "M": 93,
          "L": 79
        },
        "band": {
          "A": 1,
          "B": 16,
          "C": 19,
          "D": 35,
          "E": 77,
          "F": 95
        },
        "oddEven": {
          "ODD": 132,
          "EVEN": 111
        },
        "powerBand": {
          "A": 81,
          "B": 48,
          "C": 43,
          "D": 71
        }
      }
    },
    "d7": {
      "windowDays": 7,
      "fromYmd": "2026-04-21",
      "toYmd": "2026-04-27",
      "totalDraws": 1971,
      "select": {
        "normal": {
          "1": 339,
          "2": 348,
          "3": 348,
          "4": 336,
          "5": 365,
          "6": 347,
          "7": 358,
          "8": 364,
          "9": 351,
          "10": 350,
          "11": 357,
          "12": 329,
          "13": 351,
          "14": 367,
          "15": 358,
          "16": 326,
          "17": 357,
          "18": 335,
          "19": 369,
          "20": 373,
          "21": 376,
          "22": 359,
          "23": 362,
          "24": 356,
          "25": 356,
          "26": 332,
          "27": 365,
          "28": 321
        },
        "power": {
          "0": 200,
          "1": 189,
          "2": 211,
          "3": 214,
          "4": 205,
          "5": 176,
          "6": 182,
          "7": 202,
          "8": 200,
          "9": 192
        }
      },
      "sum": {
        "size": {
          "S": 642,
          "M": 676,
          "L": 653
        },
        "band": {
          "A": 20,
          "B": 161,
          "C": 191,
          "D": 298,
          "E": 570,
          "F": 731
        },
        "oddEven": {
          "ODD": 1024,
          "EVEN": 947
        },
        "powerBand": {
          "A": 600,
          "B": 419,
          "C": 358,
          "D": 594
        }
      }
    },
    "d30": {
      "windowDays": 30,
      "fromYmd": "2026-03-29",
      "toYmd": "2026-04-27",
      "totalDraws": 8595,
      "select": {
        "normal": {
          "1": 1500,
          "2": 1528,
          "3": 1556,
          "4": 1514,
          "5": 1503,
          "6": 1553,
          "7": 1525,
          "8": 1538,
          "9": 1535,
          "10": 1496,
          "11": 1504,
          "12": 1520,
          "13": 1533,
          "14": 1564,
          "15": 1558,
          "16": 1509,
          "17": 1532,
          "18": 1496,
          "19": 1532,
          "20": 1506,
          "21": 1592,
          "22": 1575,
          "23": 1576,
          "24": 1570,
          "25": 1577,
          "26": 1514,
          "27": 1534,
          "28": 1535
        },
        "power": {
          "0": 852,
          "1": 858,
          "2": 887,
          "3": 874,
          "4": 898,
          "5": 755,
          "6": 839,
          "7": 873,
          "8": 860,
          "9": 899
        }
      },
      "sum": {
        "size": {
          "S": 2773,
          "M": 3002,
          "L": 2820
        },
        "band": {
          "A": 86,
          "B": 645,
          "C": 891,
          "D": 1309,
          "E": 2495,
          "F": 3169
        },
        "oddEven": {
          "ODD": 4297,
          "EVEN": 4298
        },
        "powerBand": {
          "A": 2597,
          "B": 1772,
          "C": 1594,
          "D": 2632
        }
      }
    }
  }
}